{
  "$schema": "https://json-schema.org/draft/2020-12/schema",
  "type": "object",
  "required": [
    "jsonrpc",
    "id",
    "method",
    "params"
  ],
  "additionalProperties": false,
  "properties": {
    "jsonrpc": {
      "const": "2.0"
    },
    "id": {
      "$ref": "#/$defs/id"
    },
    "method": {
      "const": "ai.channels.create"
    },
    "params": {
      "$ref": "#/$defs/channelCreateParams"
    }
  },
  "$defs": {
    "id": {
      "type": "integer",
      "minimum": 1,
      "maximum": 2147483647
    },
    "channelCreateParams": {
      "type": "object",
      "required": [
        "displayName",
        "defaultBaseUrl"
      ],
      "additionalProperties": false,
      "properties": {
        "id": {
          "type": "string",
          "minLength": 1
        },
        "displayName": {
          "type": "string",
          "minLength": 1
        },
        "defaultBaseUrl": {
          "type": "string",
          "minLength": 1
        },
        "enabled": {
          "type": "boolean"
        }
      }
    }
  }
}
